{
    "display": {
        "icon": {
            "item": "minecraft:book"
        },
        "title": {
            "translate": "Story"
        },
        "description": {
            "translate": "You were happily doing nothing in the Nothingness until a male voice ripped you from it and refuses to let you return"
        },
        "frame": "task",
        "show_toast": true,
        "announce_to_chat": true,
        "hidden": false,
        "background": "minecraft:textures/gui/advancements/backgrounds/stone.png"
    },
    "criteria": {
        "crafting_table": {
            "trigger": "minecraft:inventory_changed",
            "conditions": {
                "items": [
                    {
                        "items": [
                            "minecraft:book"
                        ],
                        "count": {
                            "min": 2,
                            "max": 2
                        }
                    }
                ]
            }
        }
    },
    "requirements": [
        [
            "crafting_table"
        ]
    ]
}